code.v
module code(clk,rst,req,grant);
input clk;
input rst;
input [3:0]req;
output reg [3:0]grant;
reg [2:0] present_state,next_state;
parameter S_start=3'b000;
parameter S0=3'b001;
parameter S1=3'b010;
parameter S2=3'b011;
parameter S3=3'b100;
always @ (posedge clk or negedge rst) begin
if(!rst)
present_state<=S_start;
else
present_state<=next_state;
end
always @ (*) begin
case(present_state)
S_start: 
begin
    if(req[0])
    begin
    next_state=S0;
    end
    else if(req[1])
    begin
    next_state=S1;
    end
    else if(req[2])
    begin
        next_state=S2;
    end
    else if(req[3])
    begin
        next_state=S3;
    end
    else
    begin
    next_state=S_start;
    end
end
S0: 
begin
    if(req[1])
    begin
        next_state=S1;
    end
    else if(req[2])
    begin
        next_state=S2;
    end
    else if(req[3])
    begin
        next_state=S3;
    end
    else if(req[0])
    begin
        next_state=S0;
    end
    else
    begin
        next_state=S_start;
    end
end
S1:
begin
    if(req[2])
    begin
    next_state=S2;
    end
    else if(req[3])
    begin
        next_state=S3;
    end
    else if(req[0])
    begin
        next_state=S0;
    end
    else if(req[1])
    begin
        next_state=S1;
    end
    else 
    begin
        next_state=S_start;
    end
end 
S2:
begin
    if(req[3])
    begin
        next_state=S3;
    end
    else if(req[0])
    begin
        next_state=S0;
    end
    else if(req[1])
    begin
        next_state=S1;
    end
    else if(req[2])
    begin
        next_state=S2;
    end
    else 
    begin
        next_state=S_start;
    end
end
S3:
begin
if(req[0])
    begin
        next_state=S0;
    end
    else if(req[1])
    begin
        next_state=S1;
    end
    else if(req[2])
    begin
        next_state=S2;
    end
    else if(req[3])
    begin
        next_state=S3;
    end
    else
    begin
        next_state=S_start;
    end
end
endcase
end
always @ (*)
begin
    case(present_state)
    S0: grant=4'b0001;
    S1: grant=4'b0010;
    S2: grant=4'b0100;
    S3: grant=4'b1000;
    default: grant=4'b0000;
    endcase
end
endmodule

tb.v
module tb;
reg clk;
reg rst;
reg [3:0] req;
wire [3:0] grant;
code dut (
    .clk(clk),
    .rst(rst),
    .req(req),
    .grant(grant)
);
initial begin
    clk = 0;
    forever #5 clk = ~clk;
end

initial begin
    $dumpfile("arbiter.vcd");
    $dumpvars(0, tb);

    $monitor($time, " ns | req=%b | grant=%b | state=%d", req, grant, dut.present_state);
    rst = 0; req = 4'b0000;
    #12;
    rst = 1;
    req = 4'b0001;
    #40;

    // (40 - 80ns) req[0] and req[1] active → ping-pong
    req = 4'b0011;
    #40;

    // (80 - 120ns) req[0], req[1], req[2] active → rotates 0→1→2→0→...
    req = 4'b0111;
    #40;

    // (120 - 160ns) All requesting → rotates 0→1→2→3→...
    req = 4'b1111;
    #40;

    // (160 - 200ns) Only req[3]
    req = 4'b1000;
    #40;

    // (200 - 240ns) req[1] and req[3] → alternates 1↔3
    req = 4'b1010;
    #40;

    // (240+) No one requesting → idle
    req = 4'b0000;
    #40;

    $finish;
end

endmodule

arbiter.vcd
$date
	Sat Nov 08 17:17:54 2025
$end
$version
	Icarus Verilog
$end
$timescale
	1s
$end
$scope module tb $end
$var wire 4 ! grant [3:0] $end
$var reg 1 " clk $end
$var reg 4 # req [3:0] $end
$var reg 1 $ rst $end
$scope module dut $end
$var wire 1 % clk $end
$var wire 4 & req [3:0] $end
$var wire 1 ' rst $end
$var reg 4 ( grant [3:0] $end
$var reg 3 ) next_state [2:0] $end
$var reg 3 * present_state [2:0] $end
$upscope $end
$upscope $end
$enddefinitions $end
#0
$dumpvars
b0 *
b0 )
b0 (
0'
b0 &
0%
0$
b0 #
0"
b0 !
$end
#5
1"
1%
#10
0"
0%
#12
b1 )
b1 #
b1 &
1$
1'
#15
b1 (
b1 !
b1 *
1"
1%
#20
0"
0%
#25
1"
1%
#30
0"
0%
#35
1"
1%
#40
0"
0%
#45
1"
1%
#50
0"
0%
#52
b10 )
b11 #
b11 &
#55
b10 (
b10 !
b1 )
b10 *
1"
1%
#60
0"
0%
#65
b1 (
b1 !
b10 )
b1 *
1"
1%
#70
0"
0%
#75
b10 (
b10 !
b1 )
b10 *
1"
1%
#80
0"
0%
#85
b1 (
b1 !
b10 )
b1 *
1"
1%
#90
0"
0%
#92
b111 #
b111 &
#95
b10 (
b10 !
b11 )
b10 *
1"
1%
#100
0"
0%
#105
b100 (
b100 !
b1 )
b11 *
1"
1%
#110
0"
0%
#115
b1 (
b1 !
b10 )
b1 *
1"
1%
#120
0"
0%
#125
b10 (
b10 !
b11 )
b10 *
1"
1%
#130
0"
0%
#132
b1111 #
b1111 &
#135
b100 (
b100 !
b100 )
b11 *
1"
1%
#140
0"
0%
#145
b1000 (
b1000 !
b1 )
b100 *
1"
1%
#150
0"
0%
#155
b1 (
b1 !
b10 )
b1 *
1"
1%
#160
0"
0%
#165
b10 (
b10 !
b11 )
b10 *
1"
1%
#170
0"
0%
#172
b100 )
b1000 #
b1000 &
#175
b1000 (
b1000 !
b100 *
1"
1%
#180
0"
0%
#185
1"
1%
#190
0"
0%
#195
1"
1%
#200
0"
0%
#205
1"
1%
#210
0"
0%
#212
b10 )
b1010 #
b1010 &
#215
b10 (
b10 !
b100 )
b10 *
1"
1%
#220
0"
0%
#225
b1000 (
b1000 !
b10 )
b100 *
1"
1%
#230
0"
0%
#235
b10 (
b10 !
b100 )
b10 *
1"
1%
#240
0"
0%
#245
b1000 (
b1000 !
b10 )
b100 *
1"
1%
#250
0"
0%
#252
b0 )
b0 #
b0 &
#255
b0 (
b0 !
b0 *
1"
1%
